pinax/__init__.py
pinax/invitations/__init__.py
pinax/invitations/admin.py
pinax/invitations/apps.py
pinax/invitations/conf.py
pinax/invitations/forms.py
pinax/invitations/models.py
pinax/invitations/receivers.py
pinax/invitations/signals.py
pinax/invitations/stats.py
pinax/invitations/urls.py
pinax/invitations/views.py
pinax/invitations/management/__init__.py
pinax/invitations/management/commands/__init__.py
pinax/invitations/management/commands/add_invites.py
pinax/invitations/management/commands/infinite_invites.py
pinax/invitations/management/commands/topoff_invites.py
pinax/invitations/migrations/0001_initial.py
pinax/invitations/migrations/0002_auto_20170416_1756.py
pinax/invitations/migrations/__init__.py
pinax/invitations/templatetags/__init__.py
pinax/invitations/templatetags/pinax_invitations_tags.py
pinax/invitations/tests/__init__.py
pinax/invitations/tests/tests.py
pinax/invitations/tests/urls.py
pinax_invitations-8.0.0.dist-info/AUTHORS
pinax_invitations-8.0.0.dist-info/LICENSE
pinax_invitations-8.0.0.dist-info/METADATA
pinax_invitations-8.0.0.dist-info/WHEEL
pinax_invitations-8.0.0.dist-info/top_level.txt
pinax_invitations-8.0.0.dist-info/RECORD
